README.md
setup.py
tcppackage/tcphelp.py
tcppackage/tcprecv.py
tcppackage/tcpsend.py
tcppackage/tcpserv.py
tcppackage/tcptraffic.py
tcppackage.egg-info/PKG-INFO
tcppackage.egg-info/SOURCES.txt
tcppackage.egg-info/dependency_links.txt
tcppackage.egg-info/entry_points.txt
tcppackage.egg-info/requires.txt
tcppackage.egg-info/top_level.txt