Metadata-Version: 2.1
Name: tcppackage
Version: 0.1.1
Summary: TCP tools for network communication
Home-page: https://rasmnout.github.io
Author: Rasmnout
Author-email: rasmnout@gmail.com (https://rasmnout.github.io)
License: MIT
